alibabacloud_pvtz20180101/__init__.py
alibabacloud_pvtz20180101/client.py
alibabacloud_pvtz20180101/models/__init__.py
alibabacloud_pvtz20180101/models/_add_custom_line_request.py
alibabacloud_pvtz20180101/models/_add_custom_line_response.py
alibabacloud_pvtz20180101/models/_add_custom_line_response_body.py
alibabacloud_pvtz20180101/models/_add_resolver_endpoint_request.py
alibabacloud_pvtz20180101/models/_add_resolver_endpoint_response.py
alibabacloud_pvtz20180101/models/_add_resolver_endpoint_response_body.py
alibabacloud_pvtz20180101/models/_add_resolver_rule_request.py
alibabacloud_pvtz20180101/models/_add_resolver_rule_response.py
alibabacloud_pvtz20180101/models/_add_resolver_rule_response_body.py
alibabacloud_pvtz20180101/models/_add_user_vpc_authorization_request.py
alibabacloud_pvtz20180101/models/_add_user_vpc_authorization_response.py
alibabacloud_pvtz20180101/models/_add_user_vpc_authorization_response_body.py
alibabacloud_pvtz20180101/models/_add_zone_record_request.py
alibabacloud_pvtz20180101/models/_add_zone_record_response.py
alibabacloud_pvtz20180101/models/_add_zone_record_response_body.py
alibabacloud_pvtz20180101/models/_add_zone_request.py
alibabacloud_pvtz20180101/models/_add_zone_response.py
alibabacloud_pvtz20180101/models/_add_zone_response_body.py
alibabacloud_pvtz20180101/models/_bind_resolver_rule_vpc_request.py
alibabacloud_pvtz20180101/models/_bind_resolver_rule_vpc_response.py
alibabacloud_pvtz20180101/models/_bind_resolver_rule_vpc_response_body.py
alibabacloud_pvtz20180101/models/_bind_zone_vpc_request.py
alibabacloud_pvtz20180101/models/_bind_zone_vpc_response.py
alibabacloud_pvtz20180101/models/_bind_zone_vpc_response_body.py
alibabacloud_pvtz20180101/models/_change_zone_dns_group_request.py
alibabacloud_pvtz20180101/models/_change_zone_dns_group_response.py
alibabacloud_pvtz20180101/models/_change_zone_dns_group_response_body.py
alibabacloud_pvtz20180101/models/_check_zone_name_request.py
alibabacloud_pvtz20180101-1.3.3.dist-info/LICENSE
alibabacloud_pvtz20180101-1.3.3.dist-info/METADATA
alibabacloud_pvtz20180101-1.3.3.dist-info/WHEEL
alibabacloud_pvtz20180101-1.3.3.dist-info/top_level.txt
alibabacloud_pvtz20180101-1.3.3.dist-info/RECORD
